jpylib/__init__.py
jpylib/alerts.py
jpylib/assorted.py
jpylib/capture.py
jpylib/config.py
jpylib/fntrace.py
jpylib/iohelper.py
jpylib/kvs.py
jpylib/multiset.py
jpylib/namespace.py
jpylib/numeric.py
jpylib/options.py
jpylib/process.py
jpylib/secrets.py
jpylib/sighandler.py
jpylib/singleton.py
jpylib/stringreader.py
jpylib/table.py
jpylib/table_templates.py
jpylib/terminal.py
jpylib/text.py
jpylib/time.py
jpylib_jyrgenn-2026.201.1128.dist-info/METADATA
jpylib_jyrgenn-2026.201.1128.dist-info/WHEEL
jpylib_jyrgenn-2026.201.1128.dist-info/top_level.txt
jpylib_jyrgenn-2026.201.1128.dist-info/RECORD
