Metadata-Version: 2.4
Name: jpylib-jyrgenn
Version: 2026.201.1128
Summary: Utilities library with several more or less independent components
Home-page: https://codeberg.org/jyrgenn/jpylib/
Author: Juergen Nickelsen
Author-email: ni@w21.org
Project-URL: Documentation, https://codeberg.org/jyrgenn/jpylib/src/tag/v2026.201.1128/doc/jpylib.md
Project-URL: Source, https://codeberg.org/jyrgenn/jpylib/
Classifier: Programming Language :: Python :: 3
Classifier: License :: OSI Approved :: BSD License
Classifier: Operating System :: OS Independent
Requires-Python: >=3.6
Dynamic: author
Dynamic: author-email
Dynamic: classifier
Dynamic: description
Dynamic: description-content-type
Dynamic: home-page
Dynamic: project-url
Dynamic: requires-python
Dynamic: summary
